Workbook

Sheet 导出说明
B2: 【星火计划】财经类自媒体创作者选拔 · 每日报名与问卷评分导出模板
B3: 每日 17:00 前导出前一天报名数据 · 报名信息 + 问卷打分 + 自动定级
B5: 一、导出信息（每日填写）
B6: 数据归属日期 | C6: 前一天 00:00:00 – 23:59:59 提交的报名（按提交时间筛选），如 10 月 27 日导出填写 2026-10-26
B7: 导出截止时间 | C7: 每日 17:00 前完成
B8: 文件命名 | C8: 星火计划_报名导出_YYYYMMDD.xlsx（日期取数据归属日，即前一天）
B10: 二、工作簿结构
B11: ① 导出说明 | C11: 本页：导出口径、字段说明、评分与定级规则、使用步骤
B12: ② 报名总览 | C12: 概览主表，一行一名候选人：报名信息 + 基本信息 + 自动定级（总分、定级）+ 评审意见。总分与定级由「测评与作品明细」按评审编号自动带出
B13: ③ 测评与作品明细 | C13: 量表 6 个模块分、量表总分、Q26/Q27 简答原文与后台评分、自动总分与定级、作品信息（标题/视频/构思）。本页是问卷测评与作品的唯一录入与计算区
B15: 三、问卷评分规则
B16: 问卷构成 | C16: 共 27 题 = 25 道量表题（自评，1–5 分）+ 2 道简答题（后台评分，每题 0–10 分）
B17: 量表计分 | C17: 每题 1–5 分：5 完全符合 / 4 比较符合 / 3 一般符合 / 2 不太符合 / 1 完全不符合
B18: 六大模块 | C18: 模块一 表达沟通 5 题(满 25)；模块二 差异化特质 5 题(满 25)；模块三 跨界专业 4 题(满 20)；模块四 镜头表现 4 题(满 20)；模块五 学习力/网感 3 题(满 15)；模块六 自驱力/抗压 4 题(满 20)。量表总分满分 125
B19: 简答计分 | C19: Q26 深耕爱好与跨界领域、Q27 个人人设与差异化定位；每题 0–10 分，合计满分 20，为 ABS 孵化定级核心加分项
B20: 总分 | C20: 总分 = 量表总分(125) + 简答小计(20)，满分 145
B22: 四、自动定级规则（与系统后台完全一致）
B23: 定级 | C23: 判定条件（同时满足） | D23: 定位与资源
B24: S级·标杆IP | C24: 总分≥112 且 量表≥102 且 简答≥10 核心标杆 IP，重点全案扶持，代表品牌专业形象，承担行业发声与破圈
B25: A级·主力IP | C25: 总分≥88 且 量表≥80 且 简答≥4 中坚主力 IP，半托管陪跑孵化，重点资源倾斜，矩阵核心转化力量
B26: B级·储备IP | C26: 总分≥65 且 量表≥60 储备孵化 IP，先做图文/长文/理财通笔记，循序渐进，达标后晋升 A 级
B27: 暂不推荐·幕后支持 | C27: 未达到上述标准 仅做内容幕后撰稿、素材支持，不建议出镜做个人 IP

Sheet 报名总览
A1: 【星火计划】财经类自媒体创作者选拔 · 每日报名总览
A2: 报名信息 | G2: 基本信息 | M2: 综合定级（满分 145，自动带出） | O2: 评审
A3: 序号 | B3: 数据日期 | C3: 评审编号 | D3: 提交时间 | E3: 问卷完成时间 | F3: 审核状态 | G3: 姓名 | H3: 性别 | I3: 所属部门/团队 | J3: 现任岗位/职级 | K3: 一句话介绍 | L3: 本人账号风格 | M3: 总分(145) | N3: 系统定级 | O3: 评审意见
A4: =IF($G4="","",ROW()-3) -> 1 | B4: 2026-10-26 | C4: 示例-S-001 | D4: 2026-10-26 09:12 | E4: 2026-10-26 09:10 | F4: 初筛通过 | G4: 张三（示例） | H4: 男 | I4: 财富管理部 | J4: 投资顾问 | K4: 擅长把枯燥净值曲线讲成普通人听得懂的理财故事 | L4: 专业硬核解读 / 沉浸式图表说财经 | M4: =IF($G4="","",IFERROR(VLOOKUP($C4,测评与作品明细!$C$4:$Y$56,15,FALSE),"")) -> 141 | N4: =IF($G4="","",IFERROR(VLOOKUP($C4,测评与作品明细!$C$4:$Y$56,16,FALSE),"")) -> S级·标杆IP | O4: 示例行·使用前删除
A5: =IF($G5="","",ROW()-3) -> 2 | B5: 2026-10-26 | C5: 示例-A-002 | D5: 2026-10-26 10:35 | E5: 2026-10-26 10:33 | F5: 待初筛 | G5: 李四（示例） | H5: 女 | I5: 投研部 | J5: 行业研究员 | K5: 深耕消费行业，镜头感不错，能把行业研究讲得接地气 | L5: 专家派 / 口播解读 | M5: =IF($G5="","",IFERROR(VLOOKUP($C5,测评与作品明细!$C$4:$Y$56,15,FALSE),"")) -> 103 | N5: =IF($G5="","",IFERROR(VLOOKUP($C5,测评与作品明细!$C$4:$Y$56,16,FALSE),"")) -> A级·主力IP | O5: 示例行·使用前删除
A6: =IF($G6="","",ROW()-3) -> 3 | B6: 2026-10-26 | C6: 示例-B-003 | D6: 2026-10-26 14:02 | E6: 2026-10-26 14:00 | F6: 待定 | G6: 王五（示例） | H6: 男 | I6: 渠道管理部 | J6: 渠道经理 | K6: 乐于分享，观点输出积极，镜头表现还需打磨 | L6: 轻松幽默脱口秀 | M6: =IF($G6="","",IFERROR(VLOOKUP($C6,测评与作品明细!$C$4:$Y$56,15,FALSE),"")) -> 87 | N6: =IF($G6="","",IFERROR(VLOOKUP($C6,测评与作品明细!$C$4:$Y$56,16,FALSE),"")) -> B级·储备IP | O6: 示例行·使用前删除
A7: =IF($G7="","",ROW()-3) -> 4 | B7: 2026-10-26 | C7: 示例-X-004 | D7: 2026-10-26 16:48 | E7: 2026-10-26 16:45 | F7: 未通过 | G7: 赵六（示例） | H7: 女 | I7: 运营部 | J7: 运营专员 | K7: 愿意尝试但出镜表达偏弱、内容辨识度不足 | L7: 其它 | M7: =IF($G7="","",IFERROR(VLOOKUP($C7,测评与作品明细!$C$4:$Y$56,15,FALSE),"")) -> 48 | N7: =IF($G7="","",IFERROR(VLOOKUP($C7,测评与作品明细!$C$4:$Y$56,16,FALSE),"")) -> 暂不推荐·幕后支持 | O7: 示例行·使用前删除
A8: =IF($G8="","",ROW()-3) | M8: =IF($G8="","",IFERROR(VLOOKUP($C8,测评与作品明细!$C$4:$Y$56,15,FALSE),"")) | N8: =IF($G8="","",IFERROR(VLOOKUP($C8,测评与作品明细!$C$4:$Y$56,16,FALSE),""))
A9: =IF($G9="","",ROW()-3) | M9: =IF($G9="","",IFERROR(VLOOKUP($C9,测评与作品明细!$C$4:$Y$56,15,FALSE),"")) | N9: =IF($G9="","",IFERROR(VLOOKUP($C9,测评与作品明细!$C$4:$Y$56,16,FALSE),""))
A10: =IF($G10="","",ROW()-3) | M10: =IF($G10="","",IFERROR(VLOOKUP($C10,测评与作品明细!$C$4:$Y$56,15,FALSE),"")) | N10: =IF($G10="","",IFERROR(VLOOKUP($C10,测评与作品明细!$C$4:$Y$56,16,FALSE),""))
A11: =IF($G11="","",ROW()-3) | M11: =IF($G11="","",IFERROR(VLOOKUP($C11,测评与作品明细!$C$4:$Y$56,15,FALSE),"")) | N11: =IF($G11="","",IFERROR(VLOOKUP($C11,测评与作品明细!$C$4:$Y$56,16,FALSE),""))
A12: =IF($G12="","",ROW()-3) | M12: =IF($G12="","",IFERROR(VLOOKUP($C12,测评与作品明细!$C$4:$Y$56,15,FALSE),"")) | N12: =IF($G12="","",IFERROR(VLOOKUP($C12,测评与作品明细!$C$4:$Y$56,16,FALSE),""))
A13: =IF($G13="","",ROW()-3) | M13: =IF($G13="","",IFERROR(VLOOKUP($C13,测评与作品明细!$C$4:$Y$56,15,FALSE),"")) | N13: =IF($G13="","",IFERROR(VLOOKUP($C13,测评与作品明细!$C$4:$Y$56,16,FALSE),""))
A14: =IF($G14="","",ROW()-3) | M14: =IF($G14="","",IFERROR(VLOOKUP($C14,测评与作品明细!$C$4:$Y$56,15,FALSE),"")) | N14: =IF($G14="","",IFERROR(VLOOKUP($C14,测评与作品明细!$C$4:$Y$56,16,FALSE),""))
A15: =IF($G15="","",ROW()-3) | M15: =IF($G15="","",IFERROR(VLOOKUP($C15,测评与作品明细!$C$4:$Y$56,15,FALSE),"")) | N15: =IF($G15="","",IFERROR(VLOOKUP($C15,测评与作品明细!$C$4:$Y$56,16,FALSE),""))
A16: =IF($G16="","",ROW()-3) | M16: =IF($G16="","",IFERROR(VLOOKUP($C16,测评与作品明细!$C$4:$Y$56,15,FALSE),"")) | N16: =IF($G16="","",IFERROR(VLOOKUP($C16,测评与作品明细!$C$4:$Y$56,16,FALSE),""))
A17: =IF($G17="","",ROW()-3) | M17: =IF($G17="","",IFERROR(VLOOKUP($C17,测评与作品明细!$C$4:$Y$56,15,FALSE),"")) | N17: =IF($G17="","",IFERROR(VLOOKUP($C17,测评与作品明细!$C$4:$Y$56,16,FALSE),""))
A18: =IF($G18="","",ROW()-3) | M18: =IF($G18="","",IFERROR(VLOOKUP($C18,测评与作品明细!$C$4:$Y$56,15,FALSE),"")) | N18: =IF($G18="","",IFERROR(VLOOKUP($C18,测评与作品明细!$C$4:$Y$56,16,FALSE),""))
A19: =IF($G19="","",ROW()-3) | M19: =IF($G19="","",IFERROR(VLOOKUP($C19,测评与作品明细!$C$4:$Y$56,15,FALSE),"")) | N19: =IF($G19="","",IFERROR(VLOOKUP($C19,测评与作品明细!$C$4:$Y$56,16,FALSE),""))
... A56: =IF($G56="","",ROW()-3) | M56: =IF($G56="","",IFERROR(VLOOKUP($C56,测评与作品明细!$C$4:$Y$56,15,FALSE),"")) | N56: =IF($G56="","",IFERROR(VLOOKUP($C56,测评与作品明细!$C$4:$Y$56,16,FALSE),""))

Sheet 测评与作品明细
A1: 【星火计划】问卷测评与作品明细（量表 6 模块 · Q26/Q27 简答评分 · 作品信息）
A2: 报名信息 | E2: 量表测评（满分 125） | L2: 简答评分（满分 20） | Q2: 综合定级（满分 145） | S2: 作品信息 | Y2: 备注
A3: 序号 | B3: 数据日期 | C3: 评审编号 | D3: 姓名 | E3: 模块一 表达沟通(25) | F3: 模块二 差异化特质(25) | G3: 模块三 跨界专业(20) | H3: 模块四 镜头表现(20) | I3: 模块五 学习力网感(15) | J3: 模块六 自驱力抗压(20) | K3: 量表总分(125)（自动） | L3: Q26 深耕爱好与跨界领域（原文） | M3: Q26 得分(0–10) | N3: Q27 个人人设与差异化定位（原文） | O3: Q27 得分(0–10) | P3: 简答小计(20)（自动） | Q3: 总分(145)（自动） | R3: 系统定级（自动） | S3: 作品标题 | T3: 视频文件名 | U3: 视频时长 | V3: 视频大小 | W3: 视频链接 | X3: 作品构思 | Y3: 评分人/备注
A4: =IF($D4="","",ROW()-3) -> 1 | B4: 2026-10-26 | C4: 示例-S-001 | D4: 张三（示例） | E4: 24 | F4: 23 | G4: 19 | H4: 19 | I4: 14 | J4: 23 | K4: =IF($D4="","",IF(COUNT($E4:$J4)=6,SUM($E4:$J4),"")) -> 122 | L4: 深耕古典音乐 10 年，善用音乐对位法类比资产配置，常以乐器分工类比组合分散。 | M4: 10 | N4: 想做“把基金讲成音乐厅”的知识科普派，区别于纯念稿博主，用跨界类比让外行秒懂。 | O4: 9 | P4: =IF($D4="","",IF(AND(ISNUMBER($M4),ISNUMBER($O4)),$M4+$O4,"")) -> 19 | Q4: =IF($D4="","",IF(AND(ISNUMBER(K4),ISNUMBER(P4)),K4+P4,"")) -> 141 | R4: =IF(OR($D4="",K4=""),"",IF(AND(Q4>=112,K4>=102,P4>=10),"S级·标杆IP",IF(AND(Q4>=88,K4>=80,P4>=4),"A级·主力IP",IF(AND(Q4>=65,K4>=60),"B级·储备IP","暂不推荐·幕后支持")))) -> S级·标杆IP | S4: 《3 分钟看懂为什么要定投》 | T4: demo_S.mp4 | U4: 01:48 | V4: 36.2MB | W4: https://example.com/s | X4: 面向刚工作年轻人，用定投计算器演示长期复利，传递“尽早开始、小步坚持”的理财观。 | Y4: 示例行·使用前删除
A5: =IF($D5="","",ROW()-3) -> 2 | B5: 2026-10-26 | C5: 示例-A-002 | D5: 李四（示例） | E5: 18 | F5: 17 | G5: 17 | H5: 15 | I5: 12 | J5: 14 | K5: =IF($D5="","",IF(COUNT($E5:$J5)=6,SUM($E5:$J5),"")) -> 93 | L5: 马拉松跑者，完成 3 场全马，习惯用配速、心率区间讲投资节奏与仓位管理。 | M5: 5 | N5: 温和理性的“研究型闺蜜”，用一手行业调研讲消费，拒绝术语堆砌。 | O5: 5 | P5: =IF($D5="","",IF(AND(ISNUMBER($M5),ISNUMBER($O5)),$M5+$O5,"")) -> 10 | Q5: =IF($D5="","",IF(AND(ISNUMBER(K5),ISNUMBER(P5)),K5+P5,"")) -> 103 | R5: =IF(OR($D5="",K5=""),"",IF(AND(Q5>=112,K5>=102,P5>=10),"S级·标杆IP",IF(AND(Q5>=88,K5>=80,P5>=4),"A级·主力IP",IF(AND(Q5>=65,K5>=60),"B级·储备IP","暂不推荐·幕后支持")))) -> A级·主力IP | S5: 《消费股还能买吗》 | T5: demo_A.mp4 | U5: 01:55 | V5: 41.0MB | W5: https://example.com/a | X5: 面向有一定基础的基民，拆解消费行业估值逻辑与三条跟踪指标。 | Y5: 示例行·使用前删除
A6: =IF($D6="","",ROW()-3) -> 3 | B6: 2026-10-26 | C6: 示例-B-003 | D6: 王五（示例） | E6: 18 | F6: 17 | G6: 14 | H6: 12 | I6: 10 | J6: 14 | K6: =IF($D6="","",IF(COUNT($E6:$J6)=6,SUM($E6:$J6),"")) -> 85 | L6: 脱口秀爱好者，业余开放麦演员，擅长把生活段子改写成理财场景。 | M6: 1 | N6: 毒舌幽默的避坑型博主，人设还在打磨，与现有生活类博主区分度一般。 | O6: 1 | P6: =IF($D6="","",IF(AND(ISNUMBER($M6),ISNUMBER($O6)),$M6+$O6,"")) -> 2 | Q6: =IF($D6="","",IF(AND(ISNUMBER(K6),ISNUMBER(P6)),K6+P6,"")) -> 87 | R6: =IF(OR($D6="",K6=""),"",IF(AND(Q6>=112,K6>=102,P6>=10),"S级·标杆IP",IF(AND(Q6>=88,K6>=80,P6>=4),"A级·主力IP",IF(AND(Q6>=65,K6>=60),"B级·储备IP","暂不推荐·幕后支持")))) -> B级·储备IP | S6: 《理财小白避坑指南》 | T6: demo_B.mp4 | U6: 01:30 | V6: 28.5MB | W6: https://example.com/b | X6: 面向理财新手，情景演绎常见三个销售误导场景并给出避坑建议。 | Y6: 示例行·使用前删除
A7: =IF($D7="","",ROW()-3) -> 4 | B7: 2026-10-26 | C7: 示例-X-004 | D7: 赵六（示例） | E7: 10 | F7: 9 | G7: 8 | H7: 7 | I7: 6 | J7: 8 | K7: =IF($D7="","",IF(COUNT($E7:$J7)=6,SUM($E7:$J7),"")) -> 48 | L7: 暂无明确深耕领域，日常喜欢刷短视频、记录生活。 | M7: 0 | N7: 还没有清晰人设，想先尝试出镜，和其他博主差异不明显。 | O7: 0 | P7: =IF($D7="","",IF(AND(ISNUMBER($M7),ISNUMBER($O7)),$M7+$O7,"")) -> 0 | Q7: =IF($D7="","",IF(AND(ISNUMBER(K7),ISNUMBER(P7)),K7+P7,"")) -> 48 | R7: =IF(OR($D7="",K7=""),"",IF(AND(Q7>=112,K7>=102,P7>=10),"S级·标杆IP",IF(AND(Q7>=88,K7>=80,P7>=4),"A级·主力IP",IF(AND(Q7>=65,K7>=60),"B级·储备IP","暂不推荐·幕后支持")))) -> 暂不推荐·幕后支持 | S7: 《我的第一只基金》 | T7: demo_X.mp4 | U7: 01:20 | V7: 22.1MB | W7: https://example.com/x | X7: 记录自己第一次买基金的过程，内容偏个人随感，观点与受众定位较模糊。 | Y7: 示例行·使用前删除
A8: =IF($D8="","",ROW()-3) | K8: =IF($D8="","",IF(COUNT($E8:$J8)=6,SUM($E8:$J8),"")) | P8: =IF($D8="","",IF(AND(ISNUMBER($M8),ISNUMBER($O8)),$M8+$O8,"")) | Q8: =IF($D8="","",IF(AND(ISNUMBER(K8),ISNUMBER(P8)),K8+P8,"")) | R8: =IF(OR($D8="",K8=""),"",IF(AND(Q8>=112,K8>=102,P8>=10),"S级·标杆IP",IF(AND(Q8>=88,K8>=80,P8>=4),"A级·主力IP",IF(AND(Q8>=65,K8>=60),"B级·储备IP","暂不推荐·幕后支持"))))
A9: =IF($D9="","",ROW()-3) | K9: =IF($D9="","",IF(COUNT($E9:$J9)=6,SUM($E9:$J9),"")) | P9: =IF($D9="","",IF(AND(ISNUMBER($M9),ISNUMBER($O9)),$M9+$O9,"")) | Q9: =IF($D9="","",IF(AND(ISNUMBER(K9),ISNUMBER(P9)),K9+P9,"")) | R9: =IF(OR($D9="",K9=""),"",IF(AND(Q9>=112,K9>=102,P9>=10),"S级·标杆IP",IF(AND(Q9>=88,K9>=80,P9>=4),"A级·主力IP",IF(AND(Q9>=65,K9>=60),"B级·储备IP","暂不推荐·幕后支持"))))
A10: =IF($D10="","",ROW()-3) | K10: =IF($D10="","",IF(COUNT($E10:$J10)=6,SUM($E10:$J10),"")) | P10: =IF($D10="","",IF(AND(ISNUMBER($M10),ISNUMBER($O10)),$M10+$O10,"")) | Q10: =IF($D10="","",IF(AND(ISNUMBER(K10),ISNUMBER(P10)),K10+P10,"")) | R10: =IF(OR($D10="",K10=""),"",IF(AND(Q10>=112,K10>=102,P10>=10),"S级·标杆IP",IF(AND(Q10>=88,K10>=80,P10>=4),"A级·主力IP",IF(AND(Q10>=65,K10>=60),"B级·储备IP","暂不推荐·幕后支持"))))
A11: =IF($D11="","",ROW()-3) | K11: =IF($D11="","",IF(COUNT($E11:$J11)=6,SUM($E11:$J11),"")) | P11: =IF($D11="","",IF(AND(ISNUMBER($M11),ISNUMBER($O11)),$M11+$O11,"")) | Q11: =IF($D11="","",IF(AND(ISNUMBER(K11),ISNUMBER(P11)),K11+P11,"")) | R11: =IF(OR($D11="",K11=""),"",IF(AND(Q11>=112,K11>=102,P11>=10),"S级·标杆IP",IF(AND(Q11>=88,K11>=80,P11>=4),"A级·主力IP",IF(AND(Q11>=65,K11>=60),"B级·储备IP","暂不推荐·幕后支持"))))
A12: =IF($D12="","",ROW()-3) | K12: =IF($D12="","",IF(COUNT($E12:$J12)=6,SUM($E12:$J12),"")) | P12: =IF($D12="","",IF(AND(ISNUMBER($M12),ISNUMBER($O12)),$M12+$O12,"")) | Q12: =IF($D12="","",IF(AND(ISNUMBER(K12),ISNUMBER(P12)),K12+P12,"")) | R12: =IF(OR($D12="",K12=""),"",IF(AND(Q12>=112,K12>=102,P12>=10),"S级·标杆IP",IF(AND(Q12>=88,K12>=80,P12>=4),"A级·主力IP",IF(AND(Q12>=65,K12>=60),"B级·储备IP","暂不推荐·幕后支持"))))
A13: =IF($D13="","",ROW()-3) | K13: =IF($D13="","",IF(COUNT($E13:$J13)=6,SUM($E13:$J13),"")) | P13: =IF($D13="","",IF(AND(ISNUMBER($M13),ISNUMBER($O13)),$M13+$O13,"")) | Q13: =IF($D13="","",IF(AND(ISNUMBER(K13),ISNUMBER(P13)),K13+P13,"")) | R13: =IF(OR($D13="",K13=""),"",IF(AND(Q13>=112,K13>=102,P13>=10),"S级·标杆IP",IF(AND(Q13>=88,K13>=80,P13>=4),"A级·主力IP",IF(AND(Q13>=65,K13>=60),"B级·储备IP","暂不推荐·幕后支持"))))
A14: =IF($D14="","",ROW()-3) | K14: =IF($D14="","",IF(COUNT($E14:$J14)=6,SUM($E14:$J14),"")) | P14: =IF($D14="","",IF(AND(ISNUMBER($M14),ISNUMBER($O14)),$M14+$O14,"")) | Q14: =IF($D14="","",IF(AND(ISNUMBER(K14),ISNUMBER(P14)),K14+P14,"")) | R14: =IF(OR($D14="",K14=""),"",IF(AND(Q14>=112,K14>=102,P14>=10),"S级·标杆IP",IF(AND(Q14>=88,K14>=80,P14>=4),"A级·主力IP",IF(AND(Q14>=65,K14>=60),"B级·储备IP","暂不推荐·幕后支持"))))
A15: =IF($D15="","",ROW()-3) | K15: =IF($D15="","",IF(COUNT($E15:$J15)=6,SUM($E15:$J15),"")) | P15: =IF($D15="","",IF(AND(ISNUMBER($M15),ISNUMBER($O15)),$M15+$O15,"")) | Q15: =IF($D15="","",IF(AND(ISNUMBER(K15),ISNUMBER(P15)),K15+P15,"")) | R15: =IF(OR($D15="",K15=""),"",IF(AND(Q15>=112,K15>=102,P15>=10),"S级·标杆IP",IF(AND(Q15>=88,K15>=80,P15>=4),"A级·主力IP",IF(AND(Q15>=65,K15>=60),"B级·储备IP","暂不推荐·幕后支持"))))
A16: =IF($D16="","",ROW()-3) | K16: =IF($D16="","",IF(COUNT($E16:$J16)=6,SUM($E16:$J16),"")) | P16: =IF($D16="","",IF(AND(ISNUMBER($M16),ISNUMBER($O16)),$M16+$O16,"")) | Q16: =IF($D16="","",IF(AND(ISNUMBER(K16),ISNUMBER(P16)),K16+P16,"")) | R16: =IF(OR($D16="",K16=""),"",IF(AND(Q16>=112,K16>=102,P16>=10),"S级·标杆IP",IF(AND(Q16>=88,K16>=80,P16>=4),"A级·主力IP",IF(AND(Q16>=65,K16>=60),"B级·储备IP","暂不推荐·幕后支持"))))
A17: =IF($D17="","",ROW()-3) | K17: =IF($D17="","",IF(COUNT($E17:$J17)=6,SUM($E17:$J17),"")) | P17: =IF($D17="","",IF(AND(ISNUMBER($M17),ISNUMBER($O17)),$M17+$O17,"")) | Q17: =IF($D17="","",IF(AND(ISNUMBER(K17),ISNUMBER(P17)),K17+P17,"")) | R17: =IF(OR($D17="",K17=""),"",IF(AND(Q17>=112,K17>=102,P17>=10),"S级·标杆IP",IF(AND(Q17>=88,K17>=80,P17>=4),"A级·主力IP",IF(AND(Q17>=65,K17>=60),"B级·储备IP","暂不推荐·幕后支持"))))
A18: =IF($D18="","",ROW()-3) | K18: =IF($D18="","",IF(COUNT($E18:$J18)=6,SUM($E18:$J18),"")) | P18: =IF($D18="","",IF(AND(ISNUMBER($M18),ISNUMBER($O18)),$M18+$O18,"")) | Q18: =IF($D18="","",IF(AND(ISNUMBER(K18),ISNUMBER(P18)),K18+P18,"")) | R18: =IF(OR($D18="",K18=""),"",IF(AND(Q18>=112,K18>=102,P18>=10),"S级·标杆IP",IF(AND(Q18>=88,K18>=80,P18>=4),"A级·主力IP",IF(AND(Q18>=65,K18>=60),"B级·储备IP","暂不推荐·幕后支持"))))
A19: =IF($D19="","",ROW()-3) | K19: =IF($D19="","",IF(COUNT($E19:$J19)=6,SUM($E19:$J19),"")) | P19: =IF($D19="","",IF(AND(ISNUMBER($M19),ISNUMBER($O19)),$M19+$O19,"")) | Q19: =IF($D19="","",IF(AND(ISNUMBER(K19),ISNUMBER(P19)),K19+P19,"")) | R19: =IF(OR($D19="",K19=""),"",IF(AND(Q19>=112,K19>=102,P19>=10),"S级·标杆IP",IF(AND(Q19>=88,K19>=80,P19>=4),"A级·主力IP",IF(AND(Q19>=65,K19>=60),"B级·储备IP","暂不推荐·幕后支持"))))
... A56: =IF($D56="","",ROW()-3) | K56: =IF($D56="","",IF(COUNT($E56:$J56)=6,SUM($E56:$J56),"")) | P56: =IF($D56="","",IF(AND(ISNUMBER($M56),ISNUMBER($O56)),$M56+$O56,"")) | Q56: =IF($D56="","",IF(AND(ISNUMBER(K56),ISNUMBER(P56)),K56+P56,"")) | R56: =IF(OR($D56="",K56=""),"",IF(AND(Q56>=112,K56>=102,P56>=10),"S级·标杆IP",IF(AND(Q56>=88,K56>=80,P56>=4),"A级·主力IP",IF(AND(Q56>=65,K56>=60),"B级·储备IP","暂不推荐·幕后支持"))))

Sheet 题库与评分规则
A1: 【星火计划】问卷题库与评分规则（共 27 题）
A2: 题号 | B2: 所属模块 | C2: 题型 | D2: 题干 | E2: 满分 | F2: 评分方式
A3: Q1 | B3: 模块一·表达沟通能力 | C3: 量表题 | D3: 我说话，是为了让听得懂的人听懂，还是为了让听不懂的人也愿意听懂？我更看重后者 | E3: 5 | F3: 1–5 单选（5 完全符合 → 1 完全不符合）
A4: Q2 | C4: 量表题 | D4: 语言于我，是照亮思维的灯，还是困住思想的牢？我更多时候觉得它能照亮 | E4: 5 | F4: 1–5 单选（5 完全符合 → 1 完全不符合）
A5: Q3 | C5: 量表题 | D5: 如果沉默是金，我愿意为了把话说漂亮，舍得让金子破财 | E5: 5 | F5: 1–5 单选（5 完全符合 → 1 完全不符合）
A6: Q4 | C6: 量表题 | D6: 真正的表达，是让人记住我说的话，还是让人记住我这个人？我更看重后者 | E6: 5 | F6: 1–5 单选（5 完全符合 → 1 完全不符合）
A7: Q5 | C7: 量表题 | D7: 一个观点在我眼里常常不止一副面孔，我能看见并说出它们 | E7: 5 | F7: 1–5 单选（5 完全符合 → 1 完全不符合）
A8: Q6 | B8: 模块二·差异化特质/深耕爱好 | C8: 量表题 | D8: 在人群里，我是那个“被认出的”，还是“被遗忘的”？我更有底气相信是前者 | E8: 5 | F8: 1–5 单选（5 完全符合 → 1 完全不符合）
A9: Q7 | C9: 量表题 | D9: 我的独特不是刻意长出来的，而是它本来就在，我只是敢承认它 | E9: 5 | F9: 1–5 单选（5 完全符合 → 1 完全不符合）
A10: Q8 | C10: 量表题 | D10: 我愿意把内在那个“不一样的我”公之于众，哪怕它不合群 | E10: 5 | F10: 1–5 单选（5 完全符合 → 1 完全不符合）
A11: Q9 | C11: 量表题 | D11: 如果人生是一场叙事，我觉得我的故事线自带风格，而不是复制粘贴 | E11: 5 | F11: 1–5 单选（5 完全符合 → 1 完全不符合）
A12: Q10 | C12: 量表题 | D12: 我有一件想对它说“因为热爱，所以坚持”的事，它定义了我的一部分 | E12: 5 | F12: 1–5 单选（5 完全符合 → 1 完全不符合）
A13: Q11 | B13: 模块三·跨界专业能力 | C13: 量表题 | D13: 我相信真正的智慧是“一通百通”，两个不相关的领域往往通向同一个道理 | E13: 5 | F13: 1–5 单选（5 完全符合 → 1 完全不符合）
A14: Q12 | C14: 量表题 | D14: 我习惯从别的领域借来透镜，去看那些我以为早已看懂的金融事物 | E14: 5 | F14: 1–5 单选（5 完全符合 → 1 完全不符合）
A15: Q13 | C15: 量表题 | D15: 一个问题，我总能找到不止一种解释的坐标系，而不是只认一个标准答案 | E15: 5 | F15: 1–5 单选（5 完全符合 → 1 完全不符合）
A16: Q14 | C16: 量表题 | D16: 我掌握的跨界知识，能让我说出“外行说不出、内行没想到”的话 | E16: 5 | F16: 1–5 单选（5 完全符合 → 1 完全不符合）
A17: Q15 | B17: 模块四·镜头表现力/出镜意愿 | C17: 量表题 | D17: 被观看这件事，对我而言不是威胁，而是一种诚实的在场 | E17: 5 | F17: 1–5 单选（5 完全符合 → 1 完全不符合）
A18: Q16 | C18: 量表题 | D18: 当无数目光聚焦于我，我仍能保有“我是谁”的稳定，而不是被目光改造 | E18: 5 | F18: 1–5 单选（5 完全符合 → 1 完全不符合）
A19: Q17 | C19: 量表题 | D19: 我愿意把自己暴露在评判之下，因为我相信真实比完美更有力量 | E19: 5 | F19: 1–5 单选（5 完全符合 → 1 完全不符合）
A20: Q18 | C20: 量表题 | D20: 我能在被反复审视时保持思考的从容，而不是急着证明自己 | E20: 5 | F20: 1–5 单选（5 完全符合 → 1 完全不符合）
A21: Q19 | B21: 模块五·学习力/内容网感 | C21: 量表题 | D21: 我对世界的运作总有一种“为什么”的好奇，答案之外我还想“那然后呢” | E21: 5 | F21: 1–5 单选（5 完全符合 → 1 完全不符合）
A22: Q20 | C22: 量表题 | D22: 变化对我而言不是打扰，而是世界在向我发出新的邀请 | E22: 5 | F22: 1–5 单选（5 完全符合 → 1 完全不符合）
A23: Q21 | C23: 量表题 | D23: 我能从众人的喧嚣里，抽出那条“大家其实都在意、但没人说破”的线索 | E23: 5 | F23: 1–5 单选（5 完全符合 → 1 完全不符合）
A24: Q22 | B24: 模块六·自驱力/抗压/持续产出 | C24: 量表题 | D24: 我做一件事，意义往往在我出发时就已经存在，不需要等结果来赋予 | E24: 5 | F24: 1–5 单选（5 完全符合 → 1 完全不符合）
A25: Q23 | C25: 量表题 | D25: 当过程漫长而无反馈，我更相信“事物自有其节律”，而不是急于听到回声 | E25: 5 | F25: 1–5 单选（5 完全符合 → 1 完全不符合）
A26: Q24 | C26: 量表题 | D26: 外界的否定和误解，动摇的是我的处境，而不是我之为我的根基 | E26: 5 | F26: 1–5 单选（5 完全符合 → 1 完全不符合）
A27: Q25 | C27: 量表题 | D27: 我愿意把时间铺在一条长路上，因为我相信“长期主义”终会塑造出不一样的自己 | E27: 5 | F27: 1–5 单选（5 完全符合 → 1 完全不符合）
A28: Q26 | B28: 简答题·ABS 定级核心加分项 | C28: 简答题 | D28: 【深耕爱好与跨界领域】除金融业务之外，你深耕的爱好/跨界专业领域是什么？简单介绍你的积累和擅长输出的内容方向 参考：例如：深耕古典音乐 10 年/硬核科幻迷/马拉松跑者/心理咨询师认证……善于用音乐对位法类比资产配置 | E28: 10 | F28: 后台人工评分 0–10 分
A29: Q27 | B29: 简答题·ABS 定级核心加分项 | C29: 简答题 | D29: 【个人人设与差异化定位】如果让你做财经投教账号，你希望打造什么样的个人人设，和别的理财博主最大的区别是什么？ 参考：例如：温和理性的闺蜜型财务管家/毒舌一针见血的投顾老兵……坚决不讲晦涩术语，专注教年轻人建立第一份底仓 | E29: 10 | F29: 后台人工评分 0–10 分
A31: 自动定级阈值（量表满分 125 + 简答满分 20 = 总分满分 145）
A32: 定级 | B32: 总分 | C32: 量表分 | D32: 简答分 | E32: 定位 | F32: 资源扶持
A33: S级·标杆IP | B33: ≥112 | C33: ≥102 | D33: ≥10 | E33: 品牌标杆 IP、破圈传播 | F33: 重点全案扶持
A34: A级·主力IP | B34: ≥88 | C34: ≥80 | D34: ≥4 | E34: 中坚主力 IP | F34: 半托管陪跑、资源倾斜
A35: B级·储备IP | B35: ≥65 | C35: ≥60 | D35: — | E35: 储备孵化 IP | F35: 先图文/笔记，达标晋升
A36: 暂不推荐·幕后支持 | B36: <65 或量表<60 | C36: — | D36: — | E36: 幕后支持 | F36: 撰稿/素材，不建议出镜
